webdetect.py
webdetect-0.0.1.dist-info/LICENSE.md
webdetect-0.0.1.dist-info/METADATA
webdetect-0.0.1.dist-info/WHEEL
webdetect-0.0.1.dist-info/entry_points.txt
webdetect-0.0.1.dist-info/top_level.txt
webdetect-0.0.1.dist-info/RECORD
