Metadata-Version: 2.1
Name: webdetect
Version: 0.0.1
Summary: Detects technologies of a web page using Wappalyzer in a headless browser.
Home-page: http://github.com/0xcrypto/webdetect
Author: Vikrant Singh Chauhan
Author-email: vi@hackberry.xyz
License: MIT
Keywords: detect technology,web,wappalyzer
Platform: UNKNOWN
Classifier: Development Status :: 2 - Pre-Alpha
Classifier: Topic :: Security
Classifier: License :: Public Domain
Requires-Dist: asyncio
Requires-Dist: python-Wappalyzer
Requires-Dist: click
Requires-Dist: pyppeteer
